openghg_calscales/__init__.py
openghg_calscales/functions.py
openghg_calscales/util.py
openghg_calscales/data/convert_functions.csv
openghg_calscales/data/species_synonyms.csv
openghg_calscales-0.1.3.dist-info/licenses/LICENSE
tests/conftest.py
tests/test_functions.py
openghg_calscales-0.1.3.dist-info/METADATA
openghg_calscales-0.1.3.dist-info/WHEEL
openghg_calscales-0.1.3.dist-info/top_level.txt
openghg_calscales-0.1.3.dist-info/RECORD
