Metadata-Version: 2.4
Name: openghg_calscales
Version: 0.1.3
Summary: OpenGHG gas calibration scale conversion tool
License: MIT License
Project-URL: Homepage, https://github.com/openghg/openghg_calscales
Project-URL: Bug Tracker, https://github.com/openghg/openghg_calscales/issues
Requires-Python: >=3.9
License-File: LICENSE
Requires-Dist: pandas
Requires-Dist: numpy
Requires-Dist: networkx
Requires-Dist: xarray
Requires-Dist: sympy
Dynamic: license-file
